{
  "project_info": {
    "project_number": "868731271260",
    "project_id": "finallproject-bc273",
    "storage_bucket": "finallproject-bc273.appspot.com"
  },
  "client": [
    {
      "client_info": {
        "mobilesdk_app_id": "1:868731271260:android:835fe783eda5b903c64e99",
        "android_client_info": {
          "package_name": "com.example.lets_go"
        }
      },
      "oauth_client": [
        {
          "client_id": "868731271260-l6ds6qh5d330mt58v3oqk4mdqb4a2un0.apps.googleusercontent.com",
          "client_type": 3
        }
      ],
      "api_key": [
        {
          "current_key": "AIzaSyDkoBg6XEJtkQM8ix_5YkyTCEaR3gpCIRw"
        }
      ],
      "services": {
        "appinvite_service": {
          "other_platform_oauth_client": [
            {
              "client_id": "868731271260-l6ds6qh5d330mt58v3oqk4mdqb4a2un0.apps.googleusercontent.com",
              "client_type": 3
            }
          ]
        }
      }
    }
  ],
  "configuration_version": "1"
}